FreeAeonML/FACommon.py
FreeAeonML/FADataEDA.py
FreeAeonML/FADataPreprocess.py
FreeAeonML/FAEvaluation.py
FreeAeonML/FAFeatureSelect.py
FreeAeonML/FAModelClassify.py
FreeAeonML/FAModelCluster.py
FreeAeonML/FAModelRegression.py
FreeAeonML/FAModelSeries.py
FreeAeonML/FASample.py
FreeAeonML/FAVisualize.py
FreeAeonML/__init__.py
freeaeon_ml-0.2.0.dist-info/licenses/LICENSE
freeaeon_ml-0.2.0.dist-info/METADATA
freeaeon_ml-0.2.0.dist-info/WHEEL
freeaeon_ml-0.2.0.dist-info/top_level.txt
freeaeon_ml-0.2.0.dist-info/RECORD
