Metadata-Version: 2.4
Name: FreeAeon-ML
Version: 0.2.0
Summary: A comprehensive machine learning toolkit for data analysis, preprocessing, modeling, and evaluation.
Home-page: https://github.com/jim-xie-cn/FreeAeon-ML
Author: Jim Xie
Author-email: jim.xie.cn@outlook.com
License: MIT
Classifier: Programming Language :: Python :: 3
Classifier: License :: OSI Approved :: MIT License
Classifier: Operating System :: OS Independent
Requires-Python: >=3.6
License-File: LICENSE
Requires-Dist: matplotlib
Requires-Dist: pyecharts
Requires-Dist: seaborn
Requires-Dist: statsmodels
Requires-Dist: scikit-learn
Requires-Dist: imblearn
Requires-Dist: h2o
Requires-Dist: tqdm
Requires-Dist: networkx
Requires-Dist: pyvis
Dynamic: author
Dynamic: author-email
Dynamic: classifier
Dynamic: description
Dynamic: description-content-type
Dynamic: home-page
Dynamic: license
Dynamic: license-file
Dynamic: requires-dist
Dynamic: requires-python
Dynamic: summary
